pylint_import_restriction.py
pylint_import_restriction-0.1.5.dist-info/LICENSE
pylint_import_restriction-0.1.5.dist-info/METADATA
pylint_import_restriction-0.1.5.dist-info/WHEEL
pylint_import_restriction-0.1.5.dist-info/RECORD
